LICENSE
README.md
setup.cfg
setup.py
stock/__init__.py
stock/stock_exchange_holidays.py
stock_exchange_holidays.egg-info/PKG-INFO
stock_exchange_holidays.egg-info/SOURCES.txt
stock_exchange_holidays.egg-info/dependency_links.txt
stock_exchange_holidays.egg-info/not-zip-safe
stock_exchange_holidays.egg-info/top_level.txt
tests/__init__.py
tests/test_holidays.py