Metadata-Version: 2.1
Name: stock-exchange-holidays
Version: 0.2.0
Summary: Worldwide Stock Exchange holidays (NYSE, CME, B3 and others)
Home-page: https://github.com/leogregianin/stock-exchange-holidays
Author: Leonardo Gregianin
Author-email: leogregianin@gmail.com
License: MIT
Keywords: stock,holidays
Platform: UNKNOWN
Classifier: Programming Language :: Python
Classifier: Programming Language :: Python :: 3
Requires-Python: >=3.6
License-File: LICENSE
